locust_telemetry/__init__.py
locust_telemetry/config.py
locust_telemetry/entrypoint.py
locust_telemetry/logger.py
locust_telemetry/metadata.py
locust_telemetry/common/__init__.py
locust_telemetry/common/helpers.py
locust_telemetry/core/__init__.py
locust_telemetry/core/cli.py
locust_telemetry/core/coordinator.py
locust_telemetry/core/events.py
locust_telemetry/core/exceptions.py
locust_telemetry/core/handlers.py
locust_telemetry/core/manager.py
locust_telemetry/core/plugin.py
locust_telemetry/core/recorder.py
locust_telemetry/recorders/__init__.py
locust_telemetry/recorders/json/__init__.py
locust_telemetry/recorders/json/constants.py
locust_telemetry/recorders/json/handlers.py
locust_telemetry/recorders/json/plugin.py
locust_telemetry/recorders/json/recorder.py
locust_telemetry/recorders/otel/__init__.py
locust_telemetry/recorders/otel/exceptions.py
locust_telemetry/recorders/otel/handlers.py
locust_telemetry/recorders/otel/otel.py
locust_telemetry/recorders/otel/plugin.py
locust_telemetry/recorders/otel/recorder.py
locust_telemetry-2.1.2.dist-info/licenses/LICENSE
locust_telemetry-2.1.2.dist-info/METADATA
locust_telemetry-2.1.2.dist-info/WHEEL
locust_telemetry-2.1.2.dist-info/entry_points.txt
locust_telemetry-2.1.2.dist-info/top_level.txt
locust_telemetry-2.1.2.dist-info/RECORD
