Metadata-Version: 2.4
Name: locust-telemetry
Version: 2.1.2
Summary: A Locust plugin for emitting structured telemetry and metrics to JSON or OpenTelemetry backends.
Author-email: Swaroop Shubhakrishna Bhat <swaroopbhatk@gmail.com>
License-Expression: Apache-2.0
Project-URL: Homepage, https://locust-telemetry.readthedocs.io/en/stable/index.html
Project-URL: Documentation, https://locust-telemetry.readthedocs.io/en/latest/index.html
Project-URL: Bug-Tracker, https://github.com/platform-crew/locust-observability/issues
Keywords: locust,plugin,telemetry,observability,metrics,opentelemetry,otel,load testing,performance testing,dashboard,prometheus,grafana,loki
Classifier: Development Status :: 4 - Beta
Classifier: Intended Audience :: Developers
Classifier: Topic :: Software Development :: Testing
Classifier: Programming Language :: Python :: 3
Classifier: Programming Language :: Python :: 3.10
Classifier: Programming Language :: Python :: 3.11
Classifier: Programming Language :: Python :: 3.12
Classifier: Operating System :: OS Independent
Requires-Python: >=3.10
License-File: LICENSE
Requires-Dist: locust>=2.37.0
Requires-Dist: python-json-logger>=3.3.0
Requires-Dist: opentelemetry-api>=1.37.0
Requires-Dist: opentelemetry-sdk>=1.37.0
Requires-Dist: opentelemetry-exporter-otlp>=1.37.0
Provides-Extra: dev
Requires-Dist: pytest>=8.4.0; extra == "dev"
Requires-Dist: pytest-cov>=6.3.0; extra == "dev"
Requires-Dist: freezegun>=1.5.5; extra == "dev"
Dynamic: license-file
